src/xethhung12_minio_common/__init__.py
src/xethhung12_minio_common/common.py
src/xethhung12_minio_download_file/__init__.py
src/xethhung12_minio_download_file/__main__.py
src/xethhung12_minio_download_file/download_file.py
src/xethhung12_minio_upload_file/__init__.py
src/xethhung12_minio_upload_file/__main__.py
src/xethhung12_minio_upload_file/upload_file.py
xethhung12_minio-0.0.4.dist-info/METADATA
xethhung12_minio-0.0.4.dist-info/WHEEL
xethhung12_minio-0.0.4.dist-info/licenses/LICENSE
xethhung12_minio-0.0.4.dist-info/RECORD
