Metadata-Version: 2.1
Name: xethhung12_minio
Version: 0.0.4
Summary: A small program for downloading and uploading file to minio storage
Project-URL: Homepage, https://github.com/xh-dev/xethhung12_minio
Project-URL: Bug Tracker, https://github.com/xh-dev/xethhung12_minio/issues
Author-email: Xeth Hung <admin@xethh.me>
License-File: LICENSE
Classifier: License :: OSI Approved :: MIT License
Classifier: Operating System :: OS Independent
Classifier: Programming Language :: Python :: 3
Requires-Python: >=3.7
Requires-Dist: minio>=7.1.15
